org_cshs/__init__.py
cshs-0.1.dist-info/WHEEL
cshs-0.1.dist-info/METADATA
cshs-0.1.dist-info/RECORD
